<chromosome id="6029" primary-parent-id="2260"><neuron id="0" type="in" activation="linear"/>
<neuron id="1" type="in" activation="linear"/>
<neuron id="2" type="in" activation="linear"/>
<neuron id="3" type="in" activation="linear"/>
<neuron id="4" type="in" activation="linear"/>
<neuron id="5" type="in" activation="linear"/>
<neuron id="6" type="in" activation="linear"/>
<neuron id="7" type="out" activation="sigmoid"/>
<connection id="8" src-id="0" dest-id="7" weight="-1.5691882166933584"/>
<connection id="9" src-id="1" dest-id="7" weight="6.649340639267704"/>
<connection id="10" src-id="2" dest-id="7" weight="-1.0710539334127427"/>
<connection id="13" src-id="5" dest-id="7" weight="6.95376345785302"/>
<connection id="14" src-id="6" dest-id="7" weight="0.48269733655458186"/>
<neuron id="270" type="hid" activation="sigmoid"/>
<connection id="272" src-id="270" dest-id="7" weight="-0.039819376524872"/>
<neuron id="288" type="hid" activation="sigmoid"/>
<connection id="289" src-id="3" dest-id="288" weight="4.108723068961884"/>
<connection id="290" src-id="288" dest-id="7" weight="-1.7170254511535508"/>
<connection id="1070" src-id="3" dest-id="270" weight="-1.9701612306406266"/>
<connection id="1071" src-id="7" dest-id="270" weight="4.484447563786847"/>
<neuron id="1270" type="hid" activation="sigmoid"/>
<connection id="1271" src-id="4" dest-id="1270" weight="-0.27605148785815387"/>
<connection id="1272" src-id="1270" dest-id="270" weight="-1.691784220293049"/>
</chromosome>